data_warp/connectors/__init__.py
data_warp/connectors/base_connector.py
data_warp/connectors/database_connector.py
data_warp/connectors/file_connector.py
data_warp/connectors/sources.py
data_warp/connectors/utils.py
data_warp/pipeline/__init__.py
data_warp-0.1.6.dist-info/METADATA
data_warp-0.1.6.dist-info/WHEEL
data_warp-0.1.6.dist-info/RECORD
