Metadata-Version: 2.3
Name: data-warp
Version: 0.1.6
Summary: DataWarp is a powerful Python library that simplifies working with data files across various formats and storage locations and orchestrate data workflow for multiple backends or services.
Keywords: data-engineering,ETL,pipelines,connectors,batch-processing,stream-processing
Author: Datta Tele
Author-email: datta.tele@gmail.com
Requires-Python: >=3.10,<=3.13
Classifier: Development Status :: 4 - Beta
Classifier: Intended Audience :: Developers
Classifier: License :: OSI Approved :: MIT License
Classifier: Programming Language :: Python :: 3
Classifier: Programming Language :: Python :: 3.12
Requires-Dist: boto3 (>=1.36.8,<2.0.0)
Requires-Dist: openpyxl (>=3.1.5,<4.0.0)
Requires-Dist: pandas (>=2.0.3)
Requires-Dist: pyarrow (>=19.0.0)
Requires-Dist: retrying (>=1.3.4,<2.0.0)
Requires-Dist: setuptools (>=75.8.0)
Requires-Dist: sqlalchemy (>=2.0.38,<3.0.0)
Requires-Dist: tqdm (>=4.67.1,<5.0.0)
Project-URL: Documentation, https://github.com/dattatele/data-buddy/wiki
Project-URL: Homepage, https://github.com/dattatele/data-buddy
Project-URL: Issue Tracker, https://github.com/dattatele/data-buddy/issues
Project-URL: Source, https://github.com/dattatele/data-buddy
